alert.py
namespace.py
octacli.py
policy.py
service.py
tokens.py
user.py
octacli-0.1.1.dist-info/DESCRIPTION.rst
octacli-0.1.1.dist-info/METADATA
octacli-0.1.1.dist-info/RECORD
octacli-0.1.1.dist-info/WHEEL
octacli-0.1.1.dist-info/entry_points.txt
octacli-0.1.1.dist-info/metadata.json
octacli-0.1.1.dist-info/top_level.txt
